<annotation>
	<folder>images</folder>
	<filename>image272.jpg</filename>
	<path>/home/hrl/Downloads/images/image272.jpg</path>
	<source>
		<database>Unknown</database>
	</source>
	<size>
		<width>3840</width>
		<height>2160</height>
		<depth>3</depth>
	</size>
	<segmented>0</segmented>
	<object>
		<name>kick</name>
		<pose>Unspecified</pose>
		<truncated>0</truncated>
		<difficult>0</difficult>
		<bndbox>
			<xmin>1346</xmin>
			<ymin>1297</ymin>
			<xmax>2178</xmax>
			<ymax>2124</ymax>
		</bndbox>
	</object>
	<object>
		<name>grasp</name>
		<pose>Unspecified</pose>
		<truncated>0</truncated>
		<difficult>0</difficult>
		<bndbox>
			<xmin>8</xmin>
			<ymin>6</ymin>
			<xmax>537</xmax>
			<ymax>530</ymax>
		</bndbox>
	</object>
</annotation>
