<annotation>
	<folder>images</folder>
	<filename>image121.jpg</filename>
	<path>/home/hrl/Downloads/images/image121.jpg</path>
	<source>
		<database>Unknown</database>
	</source>
	<size>
		<width>3840</width>
		<height>2160</height>
		<depth>3</depth>
	</size>
	<segmented>0</segmented>
	<object>
		<name>push</name>
		<pose>Unspecified</pose>
		<truncated>0</truncated>
		<difficult>0</difficult>
		<bndbox>
			<xmin>581</xmin>
			<ymin>227</ymin>
			<xmax>1061</xmax>
			<ymax>818</ymax>
		</bndbox>
	</object>
	<object>
		<name>kick</name>
		<pose>Unspecified</pose>
		<truncated>0</truncated>
		<difficult>0</difficult>
		<bndbox>
			<xmin>1205</xmin>
			<ymin>821</ymin>
			<xmax>1484</xmax>
			<ymax>1100</ymax>
		</bndbox>
	</object>
	<object>
		<name>grasp</name>
		<pose>Unspecified</pose>
		<truncated>0</truncated>
		<difficult>0</difficult>
		<bndbox>
			<xmin>2246</xmin>
			<ymin>1162</ymin>
			<xmax>2808</xmax>
			<ymax>1709</ymax>
		</bndbox>
	</object>
</annotation>
