<annotation>
	<folder>images</folder>
	<filename>image215.jpg</filename>
	<path>/home/hrl/Downloads/images/image215.jpg</path>
	<source>
		<database>Unknown</database>
	</source>
	<size>
		<width>3840</width>
		<height>2160</height>
		<depth>3</depth>
	</size>
	<segmented>0</segmented>
	<object>
		<name>grasp</name>
		<pose>Unspecified</pose>
		<truncated>0</truncated>
		<difficult>0</difficult>
		<bndbox>
			<xmin>2469</xmin>
			<ymin>444</ymin>
			<xmax>2793</xmax>
			<ymax>630</ymax>
		</bndbox>
	</object>
	<object>
		<name>push</name>
		<pose>Unspecified</pose>
		<truncated>0</truncated>
		<difficult>0</difficult>
		<bndbox>
			<xmin>2781</xmin>
			<ymin>724</ymin>
			<xmax>3425</xmax>
			<ymax>1403</ymax>
		</bndbox>
	</object>
	<object>
		<name>kick</name>
		<pose>Unspecified</pose>
		<truncated>0</truncated>
		<difficult>0</difficult>
		<bndbox>
			<xmin>1058</xmin>
			<ymin>797</ymin>
			<xmax>1328</xmax>
			<ymax>1056</ymax>
		</bndbox>
	</object>
	<object>
		<name>grasp</name>
		<pose>Unspecified</pose>
		<truncated>1</truncated>
		<difficult>0</difficult>
		<bndbox>
			<xmin>2275</xmin>
			<ymin>1862</ymin>
			<xmax>2789</xmax>
			<ymax>2160</ymax>
		</bndbox>
	</object>
	<object>
		<name>grasp</name>
		<pose>Unspecified</pose>
		<truncated>0</truncated>
		<difficult>0</difficult>
		<bndbox>
			<xmin>2</xmin>
			<ymin>1583</ymin>
			<xmax>461</xmax>
			<ymax>1977</ymax>
		</bndbox>
	</object>
</annotation>
