<annotation>
	<folder>images</folder>
	<filename>image112.jpg</filename>
	<path>/home/hrl/Downloads/images/image112.jpg</path>
	<source>
		<database>Unknown</database>
	</source>
	<size>
		<width>3840</width>
		<height>2160</height>
		<depth>3</depth>
	</size>
	<segmented>0</segmented>
	<object>
		<name>push</name>
		<pose>Unspecified</pose>
		<truncated>0</truncated>
		<difficult>0</difficult>
		<bndbox>
			<xmin>1522</xmin>
			<ymin>180</ymin>
			<xmax>1805</xmax>
			<ymax>483</ymax>
		</bndbox>
	</object>
	<object>
		<name>kick</name>
		<pose>Unspecified</pose>
		<truncated>0</truncated>
		<difficult>0</difficult>
		<bndbox>
			<xmin>1966</xmin>
			<ymin>544</ymin>
			<xmax>2158</xmax>
			<ymax>768</ymax>
		</bndbox>
	</object>
	<object>
		<name>grasp</name>
		<pose>Unspecified</pose>
		<truncated>0</truncated>
		<difficult>0</difficult>
		<bndbox>
			<xmin>2755</xmin>
			<ymin>786</ymin>
			<xmax>3184</xmax>
			<ymax>1127</ymax>
		</bndbox>
	</object>
	<object>
		<name>kick</name>
		<pose>Unspecified</pose>
		<truncated>0</truncated>
		<difficult>0</difficult>
		<bndbox>
			<xmin>2343</xmin>
			<ymin>1556</ymin>
			<xmax>2840</xmax>
			<ymax>2088</ymax>
		</bndbox>
	</object>
	<object>
		<name>kick</name>
		<pose>Unspecified</pose>
		<truncated>0</truncated>
		<difficult>0</difficult>
		<bndbox>
			<xmin>225</xmin>
			<ymin>1662</ymin>
			<xmax>705</xmax>
			<ymax>2130</ymax>
		</bndbox>
	</object>
</annotation>
