<annotation>
	<folder>images</folder>
	<filename>image81.jpg</filename>
	<path>/home/hrl/Downloads/images/image81.jpg</path>
	<source>
		<database>Unknown</database>
	</source>
	<size>
		<width>3840</width>
		<height>2160</height>
		<depth>3</depth>
	</size>
	<segmented>0</segmented>
	<object>
		<name>kick</name>
		<pose>Unspecified</pose>
		<truncated>0</truncated>
		<difficult>0</difficult>
		<bndbox>
			<xmin>3269</xmin>
			<ymin>409</ymin>
			<xmax>3396</xmax>
			<ymax>586</ymax>
		</bndbox>
	</object>
	<object>
		<name>kick</name>
		<pose>Unspecified</pose>
		<truncated>1</truncated>
		<difficult>0</difficult>
		<bndbox>
			<xmin>3543</xmin>
			<ymin>1056</ymin>
			<xmax>3840</xmax>
			<ymax>1457</ymax>
		</bndbox>
	</object>
	<object>
		<name>kick</name>
		<pose>Unspecified</pose>
		<truncated>0</truncated>
		<difficult>0</difficult>
		<bndbox>
			<xmin>1996</xmin>
			<ymin>753</ymin>
			<xmax>2281</xmax>
			<ymax>1071</ymax>
		</bndbox>
	</object>
	<object>
		<name>grasp</name>
		<pose>Unspecified</pose>
		<truncated>0</truncated>
		<difficult>0</difficult>
		<bndbox>
			<xmin>2258</xmin>
			<ymin>241</ymin>
			<xmax>2358</xmax>
			<ymax>433</ymax>
		</bndbox>
	</object>
	<object>
		<name>grasp</name>
		<pose>Unspecified</pose>
		<truncated>0</truncated>
		<difficult>0</difficult>
		<bndbox>
			<xmin>313</xmin>
			<ymin>1171</ymin>
			<xmax>1022</xmax>
			<ymax>1709</ymax>
		</bndbox>
	</object>
	<object>
		<name>push</name>
		<pose>Unspecified</pose>
		<truncated>0</truncated>
		<difficult>0</difficult>
		<bndbox>
			<xmin>1205</xmin>
			<ymin>133</ymin>
			<xmax>1846</xmax>
			<ymax>709</ymax>
		</bndbox>
	</object>
</annotation>
